randimage/__init__.py
randimage/coloredpath.py
randimage/masks.py
randimage/paths.py
randimage/utils.py
randimage-1.2.dist-info/LICENSE
randimage-1.2.dist-info/METADATA
randimage-1.2.dist-info/WHEEL
randimage-1.2.dist-info/top_level.txt
randimage-1.2.dist-info/RECORD
