Metadata-Version: 2.1
Name: randimage
Version: 1.2
Summary: Creates random images
Home-page: https://github.com/nareto/randimage
Author: Renato Budinich
Author-email: rennabh@gmail.com
License: MIT
Platform: UNKNOWN
